soon/__init__.py
soon/soon.py
soon-0.2.dist-info/LICENSE
soon-0.2.dist-info/METADATA
soon-0.2.dist-info/WHEEL
soon-0.2.dist-info/top_level.txt
soon-0.2.dist-info/RECORD
