Metadata-Version: 2.1
Name: soon
Version: 0.2
Summary: 
Home-page: https://github.com/dotpot/soon
Author: Lukas Šalkauskas
Author-email: halfas.online@gmail.com
License: MIT License (See LICENSE)
Platform: UNKNOWN
Requires-Python: >=3.7.0
Requires-Dist: futures (>=2.2.0)
